README.md
setup.py
pyjuque/Bot.py
pyjuque/Utils.py
pyjuque/__init__.py
pyjuque.egg-info/PKG-INFO
pyjuque.egg-info/SOURCES.txt
pyjuque.egg-info/dependency_links.txt
pyjuque.egg-info/requires.txt
pyjuque.egg-info/top_level.txt
pyjuque/Engine/Backtester.py
pyjuque/Engine/BacktesterSundayTheQuant.py
pyjuque/Engine/BotController.py
pyjuque/Engine/Database.py
pyjuque/Engine/GridBotController.py
pyjuque/Engine/OrderManager.py
pyjuque/Engine/__init__.py
pyjuque/Engine/Models/BotModels.py
pyjuque/Engine/Models/CandlestickModel.py
pyjuque/Engine/Models/Utils.py
pyjuque/Engine/Models/__init__.py
pyjuque/Exchanges/Binance.py
pyjuque/Exchanges/BinanceOrderBook.py
pyjuque/Exchanges/CcxtExchange.py
pyjuque/Exchanges/__init__.py
pyjuque/Exchanges/Base/BaseExchange.py
pyjuque/Exchanges/Base/Exceptions.py
pyjuque/Exchanges/Base/__init__.py
pyjuque/Plotting/__init__.py
pyjuque/Strategies/__init__.py
tests/test_Models.py
tests/utils.py