Metadata-Version: 2.1
Name: pyjuque
Version: 0.1.1.4
Summary: 'Juju' Quant Engine for Python
Home-page: https://github.com/tudorelu/pyjuque
Author: Tudor Barbulescu
Author-email: hello@tudorbarbulescu.com
License: MIT
Platform: UNKNOWN
